bottle_rest/__init__.py
bottle_rest/bottle_rest.py
bottle_restful-0.0.1.dist-info/LICENSE
bottle_restful-0.0.1.dist-info/METADATA
bottle_restful-0.0.1.dist-info/WHEEL
bottle_restful-0.0.1.dist-info/top_level.txt
bottle_restful-0.0.1.dist-info/RECORD
